LICENCE
MANIFEST.in
README.md
setup.py
django_fiat.egg-info/PKG-INFO
django_fiat.egg-info/SOURCES.txt
django_fiat.egg-info/dependency_links.txt
django_fiat.egg-info/not-zip-safe
django_fiat.egg-info/top_level.txt
fiat/__init__.py
fiat/admin.py
fiat/enums.py
fiat/models.py
fiat/signals.py
fiat/fixtures/initial_data.json
fiat/tests/__init__.py
fiat/tests/tests.py
testproject/__init__.py
testproject/manage.py
testproject/runtests.py
testproject/settings.py
testproject/settings_admin.py
testproject/urls.py
testproject/wsgi.py